django_superset_integration/__init__.py
django_superset_integration/admin.py
django_superset_integration/apps.py
django_superset_integration/fetch_superset_guest_token.py
django_superset_integration/forms.py
django_superset_integration/models.py
django_superset_integration/urls.py
django_superset_integration/migrations/0001_initial.py
django_superset_integration/migrations/0002_supersetdashboard_app_name.py
django_superset_integration/migrations/__init__.py
django_superset_integration/static/django_superset_integration/css/django-superset-integration.css
django_superset_integration/static/django_superset_integration/js/display-dashboard.js
django_superset_integration/static/django_superset_integration/js/get-guest-token.js
django_superset_integration/static/django_superset_integration/js/superset-embedded-sdk.js
django_superset_integration/templates/django_superset_integration/superset-integration.html
django_superset_integration-0.1.22.dist-info/METADATA
django_superset_integration-0.1.22.dist-info/WHEEL
django_superset_integration-0.1.22.dist-info/top_level.txt
django_superset_integration-0.1.22.dist-info/RECORD
